profiler_cub/__init__.py
profiler_cub/__main__.py
profiler_cub/_stats.py
profiler_cub/api.py
profiler_cub/common.py
profiler_cub/core.py
profiler_cub/display.py
profiler_cub/models.py
profiler_cub/py.typed
profiler_cub/_internal/__init__.py
profiler_cub/_internal/_cmds.py
profiler_cub/_internal/_exit_code.py
profiler_cub/_internal/_info.py
profiler_cub/_internal/_version.py
profiler_cub/_internal/_version.pyi
profiler_cub/_internal/_versioning.py
profiler_cub/_internal/cli.py
profiler_cub/_internal/debug.py
profiler_cub-0.0.9.dist-info/METADATA
profiler_cub-0.0.9.dist-info/WHEEL
profiler_cub-0.0.9.dist-info/entry_points.txt
profiler_cub-0.0.9.dist-info/RECORD
