Metadata-Version: 2.4
Name: profiler-cub
Version: 0.0.9
Summary: A beautiful profiler for Python projects with various options
Author-email: chaz <bright.lid5647@fastmail.com>
Requires-Python: >=3.12
Requires-Dist: funcy-bear>=0.0.25
Requires-Dist: lazy-bear>=0.0.11
Requires-Dist: rich>=14.2.0
